pzserver/__init__.py
pzserver/_version.py
pzserver/catalog.py
pzserver/communicate.py
pzserver/core.py
pzserver/pipeline.py
pzserver/process.py
pzserver/product.py
pzserver/upload.py
pzserver-0.3.2.dist-info/licenses/LICENSE
pzserver-0.3.2.dist-info/METADATA
pzserver-0.3.2.dist-info/WHEEL
pzserver-0.3.2.dist-info/top_level.txt
pzserver-0.3.2.dist-info/RECORD
