Metadata-Version: 2.4
Name: pzserver
Version: 0.3.2
Author-email: LIneA <itteam@linea.org.br>
License: MIT License
Classifier: Development Status :: 4 - Beta
Classifier: License :: OSI Approved :: MIT License
Classifier: Intended Audience :: Developers
Classifier: Intended Audience :: Science/Research
Classifier: Operating System :: OS Independent
Classifier: Programming Language :: Python :: 3.7
Classifier: Programming Language :: Python :: 3.8
Classifier: Programming Language :: Python :: 3.9
Classifier: Programming Language :: Python :: 3.10
Classifier: Programming Language :: Python :: 3.11
Classifier: Programming Language :: Python :: 3.12
Requires-Python: <3.13,>=3.7
License-File: LICENSE
Requires-Dist: astropy<8,>=6
Requires-Dist: Deprecated<2,>=1
Requires-Dist: h5py<4,>=3
Requires-Dist: ipython<9,>=8
Requires-Dist: Jinja2<4,>=3
Requires-Dist: matplotlib<4,>=3
Requires-Dist: numpy<3,>=1
Requires-Dist: pandas<3,>=2
Requires-Dist: pyarrow<18,>=17
Requires-Dist: pydantic<3,>=2
Requires-Dist: requests<3,>=2
Requires-Dist: tables-io<2,>=1
Provides-Extra: dev
Requires-Dist: pytest; extra == "dev"
Requires-Dist: pytest-cov; extra == "dev"
Requires-Dist: pre-commit; extra == "dev"
Requires-Dist: sphinx<8,>=7.0.0; extra == "dev"
Requires-Dist: sphinx_rtd_theme<2,>=1.2.0; extra == "dev"
Requires-Dist: sphinx-autoapi<4,>=3.0.0; extra == "dev"
Requires-Dist: pylint; extra == "dev"
Requires-Dist: ipykernel; extra == "dev"
Requires-Dist: nbconvert; extra == "dev"
Requires-Dist: nbsphinx; extra == "dev"
Requires-Dist: ipython; extra == "dev"
Requires-Dist: jupyterlab; extra == "dev"
Requires-Dist: matplotlib; extra == "dev"
Requires-Dist: ghp-import; extra == "dev"
Dynamic: license-file
